3-8-bit-up-down-counter/design.v
/*
Project 3: Synchronou counter with control signal to toggle up/down
Verigy with directed stimulus
*/

module up_down_counter(input up_down,
                       input reset,
                       input clk,
                       input load,
                       input [7:0] data,
                       output reg [7:0] count);
    initial begin
        count <= 8'h00;
    end
    always @(posedge clk or posedge reset) begin
        if(reset) begin
            count <= 8'h00;
        end
        else if(load) begin
            count <= data;
        end
        else if(up_down) begin
            count <= count + 1;
        end
        else begin
            count <= count - 1;
        end
        
    end
  
endmodule

3-8-bit-up-down-counter/testbench.sv
module DUT;
  reg up_down, reset, clk, load;
  reg [7:0] data;
  wire [7:0] count;
  up_down_counter counter_tb(up_down, reset, clk, load, data, count);
  initial begin
    clk <= 0;
    forever #5 clk <= !clk;
  end
    
  initial begin
    $dumpfile("8-bit-up-down-counter.vcd");
    $dumpvars(0, DUT);
    $monitor ("up_down=0x%0h reset=0x%0h clk=0x%0h load=0x%0h data=0x%0h count=0x%0h", up_down, reset, clk, load, data, count);
    
    up_down <= 0;
    reset <= 0;
    load <= 0;
    #20;
    up_down <= 1;
    #30;
    reset <= 1;
    #10;
    reset <= 0;
    load <= 1;
    data <= 8'h14;
    #10;
    load <= 0;
    #30;
    up_down <= 0;
    #30;

    $finish();
  end
endmodule

3-8-bit-up-down-counter/8-bit-up-down-counter.vcd
$date
	Tue Dec 30 15:22:50 2025
$end
$version
	Icarus Verilog
$end
$timescale
	1s
$end
$scope module DUT $end
$var wire 8 ! count [7:0] $end
$var reg 1 " clk $end
$var reg 8 # data [7:0] $end
$var reg 1 $ load $end
$var reg 1 % reset $end
$var reg 1 & up_down $end
$scope module counter_tb $end
$var wire 1 " clk $end
$var wire 8 ' data [7:0] $end
$var wire 1 $ load $end
$var wire 1 % reset $end
$var wire 1 & up_down $end
$var reg 8 ( count [7:0] $end
$upscope $end
$upscope $end
$enddefinitions $end
$comment Show the parameter values. $end
$dumpall
$end
#0
$dumpvars
b0 (
bx '
0&
0%
0$
bx #
0"
b0 !
$end
#5
b11111111 !
b11111111 (
1"
#10
0"
#15
b11111110 !
b11111110 (
1"
#20
0"
1&
#25
b11111111 !
b11111111 (
1"
#30
0"
#35
b0 !
b0 (
1"
#40
0"
#45
b1 !
b1 (
1"
#50
b0 !
b0 (
0"
1%
#55
1"
#60
0"
b10100 #
b10100 '
1$
0%
#65
b10100 !
b10100 (
1"
#70
0"
0$
#75
b10101 !
b10101 (
1"
#80
0"
#85
b10110 !
b10110 (
1"
#90
0"
#95
b10111 !
b10111 (
1"
#100
0"
0&
#105
b10110 !
b10110 (
1"
#110
0"
#115
b10101 !
b10101 (
1"
#120
0"
#125
b10100 !
b10100 (
1"
